[
  {
    "__TYPE__": "SharedSliceContent",
    "variation": "default",
    "primary": {
      "title": {
        "__TYPE__": "StructuredTextContent",
        "value": [
          {
            "type": "heading1",
            "content": {
              "text": "Manner"
            }
          }
        ]
      },
      "description": {
        "__TYPE__": "StructuredTextContent",
        "value": [
          {
            "type": "paragraph",
            "content": {
              "text": "Sunt veniam tempor consectetur ea excepteur magna ea ex nulla."
            }
          }
        ]
      },
      "image": {
        "__TYPE__": "ImageContent",
        "origin": {
          "id": "main",
          "url": "https://images.unsplash.com/photo-1504198070170-4ca53bb1c1fa",
          "width": 2747,
          "height": 4120
        },
        "url": "https://images.unsplash.com/photo-1504198070170-4ca53bb1c1fa",
        "width": 2747,
        "height": 4120,
        "edit": {
          "zoom": 1,
          "crop": {
            "x": 0,
            "y": 0
          },
          "background": "transparent"
        },
        "thumbnails": {}
      },
      "link": {
        "__TYPE__": "LinkContent",
        "value": {
          "__TYPE__": "ExternalLink",
          "url": "https://prismic.io"
        }
      },
      "theme": {
        "__TYPE__": "FieldContent",
        "value": "Brown",
        "type": "Select"
      }
    },
    "items": [
      {
        "__TYPE__": "GroupItemContent",
        "value": []
      }
    ]
  },
  {
    "__TYPE__": "SharedSliceContent",
    "variation": "fullWidthImage",
    "primary": {
      "title": {
        "__TYPE__": "StructuredTextContent",
        "value": [
          {
            "type": "heading1",
            "content": {
              "text": "Unusual"
            }
          }
        ]
      },
      "description": {
        "__TYPE__": "StructuredTextContent",
        "value": [
          {
            "type": "paragraph",
            "content": {
              "text": "Esse fugiat sunt ex ipsum exercitation."
            }
          }
        ]
      },
      "theme": {
        "__TYPE__": "FieldContent",
        "value": "Dark",
        "type": "Select"
      },
      "image": {
        "__TYPE__": "ImageContent",
        "origin": {
          "id": "main",
          "url": "https://images.unsplash.com/photo-1587614295999-6c1c13675117",
          "width": 3810,
          "height": 5715
        },
        "url": "https://images.unsplash.com/photo-1587614295999-6c1c13675117",
        "width": 3810,
        "height": 5715,
        "edit": {
          "zoom": 1,
          "crop": {
            "x": 0,
            "y": 0
          },
          "background": "transparent"
        },
        "thumbnails": {}
      },
      "link": {
        "__TYPE__": "LinkContent",
        "value": {
          "__TYPE__": "ExternalLink",
          "url": "https://slicemachine.dev"
        }
      }
    },
    "items": [
      {
        "__TYPE__": "GroupItemContent",
        "value": []
      }
    ]
  }
]